{
    "_id": "5ac3b934156ae10c4430e83c",
    "customization_seller": true,
    "name": "Аршавир Саркисович",
    "surname": "Абрамян",
    "nickname": "Ragman",
    "location": "",
    "avatar": "/files/trader/avatar/5ac3b86a86f77461491d1ad8.jpg",
    "balance_rub": 80000000,
    "balance_dol": 0,
    "balance_eur": 0,
    "unlockedByDefault": true,
    "discount": 0,
    "discount_end": 0,
    "buyer_up": false,
    "currency": "RUB",
    "nextResupply": 3600,
    "repair": {
        "availability": false,
        "quality": "1",
        "excluded_id_list": [],
        "excluded_category": [],
        "currency": "5449016a4bdc2d6f028b456f",
        "currency_coefficient": 1
    },
    "insurance": {
        "availability": true,
        "min_payment": 50000,
        "min_return_hour": 4,
        "max_return_hour": 8,
        "max_storage_time": 144,
        "excluded_category": []
    },
    "medic": false,
    "gridHeight": 200,
    "loyaltyLevels": [{
            "minLevel": 1,
            "minSalesSum": 0,
            "minStanding": 0,
            "buy_price_coef": 53,
            "repair_price_coef": 175,
            "insurance_price_coef": 300,
            "exchange_price_coef": 0,
            "heal_price_coef": 0
        }, {
            "minLevel": "20",
            "minSalesSum": 500000,
            "minStanding": 0,
            "buy_price_coef": 48,
            "repair_price_coef": 170,
            "insurance_price_coef": "300",
            "exchange_price_coef": 0,
            "heal_price_coef": 0
        }, {
            "minLevel": "36",
            "minSalesSum": 800000,
            "minStanding": 0.3,
            "buy_price_coef": 43,
            "repair_price_coef": 165,
            "insurance_price_coef": "300",
            "exchange_price_coef": 0,
            "heal_price_coef": 0
        }, {
            "minLevel": "48",
            "minSalesSum": 1400000,
            "minStanding": 0.6,
            "buy_price_coef": 38,
            "repair_price_coef": 160,
            "insurance_price_coef": "300",
            "exchange_price_coef": 0,
            "heal_price_coef": 0
        }
    ],
    "sell_category": [
		"5b47574386f77428ca22b33f"
	]
}
